{
  "name": "Blindness/Deafness",
  "type": "spell",
  "img": "modules/foundry-core-srd-5e/assets/spells/blindnessdeafness.png",
  "system": {
    "description": {
      "value": "<p><strong>Level 2</strong> Transmutation</p>\n<p><strong>Casting Time:</strong> 1 action</p>\n<p><strong>Range:</strong> 120 feet</p>\n<p><strong>Components:</strong> V</p>\n<p><strong>Duration:</strong> 1 minute</p>\n\nOne creature that you can see within range must succeed on a Constitution saving throw, or it has the Blinded|XPHB or Deafened|XPHB condition (your choice) for the duration. At the end of each of its turns, the target repeats the save, ending the spell on itself on a success.\n\n<p><strong>At Higher Levels:</strong> You can target one additional creature for each spell slot level above 2.</p>",
      "chat": "",
      "unidentified": ""
    },
    "source": "SRD 5.2.1",
    "activation": {
      "type": "action",
      "cost": 1,
      "condition": ""
    },
    "duration": {
      "value": 1,
      "units": "minute"
    },
    "target": {
      "value": null,
      "width": null,
      "units": "",
      "type": "creature"
    },
    "range": {
      "value": 120,
      "long": null,
      "units": "ft"
    },
    "uses": {
      "value": null,
      "max": "",
      "per": null,
      "recovery": ""
    },
    "consume": {
      "type": "",
      "target": null,
      "amount": null
    },
    "ability": "",
    "actionType": "save",
    "attackBonus": "",
    "chatFlavor": "",
    "critical": {
      "threshold": null,
      "damage": ""
    },
    "damage": {
      "parts": [],
      "versatile": ""
    },
    "formula": "",
    "save": {
      "ability": "con",
      "dc": null,
      "scaling": "spell"
    },
    "level": 2,
    "school": "trs",
    "components": {
      "value": "",
      "vocal": true,
      "somatic": false,
      "material": false,
      "ritual": false,
      "concentration": false
    },
    "materials": {
      "value": "",
      "consumed": false,
      "cost": 0,
      "supply": 0
    },
    "preparation": {
      "mode": "prepared",
      "prepared": false
    },
    "scaling": {
      "mode": "level",
      "formula": ""
    }
  },
  "flags": {
    "foundry-core-srd-5e": {
      "srdSource": "XPHB",
      "srd52": true,
      "page": 248,
      "school": "T",
      "classes": [],
      "_srdData": {
        "name": "Blindness/Deafness",
        "source": "XPHB",
        "page": 248,
        "srd52": true,
        "basicRules2024": true,
        "level": 2,
        "school": "T",
        "time": [
          {
            "number": 1,
            "unit": "action"
          }
        ],
        "range": {
          "type": "point",
          "distance": {
            "type": "feet",
            "amount": 120
          }
        },
        "components": {
          "v": true
        },
        "duration": [
          {
            "type": "timed",
            "duration": {
              "type": "minute",
              "amount": 1
            }
          }
        ],
        "entries": [
          "One creature that you can see within range must succeed on a Constitution saving throw, or it has the {@condition Blinded|XPHB} or {@condition Deafened|XPHB} condition (your choice) for the duration. At the end of each of its turns, the target repeats the save, ending the spell on itself on a success."
        ],
        "entriesHigherLevel": [
          {
            "type": "entries",
            "name": "Using a Higher-Level Spell Slot",
            "entries": [
              "You can target one additional creature for each spell slot level above 2."
            ]
          }
        ],
        "conditionInflict": [
          "blinded",
          "deafened"
        ],
        "savingThrow": [
          "constitution"
        ],
        "miscTags": [
          "SCT",
          "SGT"
        ],
        "areaTags": [
          "ST"
        ]
      }
    }
  }
}