{
  "id": "foundry-core-srd-5e",
  "title": "Foundry Core SRD 5e",
  "description": "D&D 5e System Reference Document 5.2.1 implementation for Foundry VTT. Includes 60+ core concept definitions: 15 conditions, 15 hazards, 14 actions, 13 damage types, 7 activities, 4 travel paces, plus all official 5e species, classes, monsters, items, spells, and rules.",
  "version": "0.1.0",
  "authors": [
    {
      "name": "Core Concepts Contributors"
    }
  ],
  "compatibility": {
    "minimum": "11",
    "verified": "11",
    "maximum": "12"
  },
  "esmodules": [
    "scripts/init.mjs"
  ],
  "styles": [
    "styles/srd-5e.css"
  ],
  "packs": [
    {
      "name": "srd-species",
      "label": "SRD 5e Species",
      "path": "packs/species",
      "type": "Item",
      "system": "dnd5e",
      "private": false
    },
    {
      "name": "srd-classes",
      "label": "SRD 5e Classes",
      "path": "packs/classes",
      "type": "Item",
      "system": "dnd5e",
      "private": false
    },
    {
      "name": "srd-subclasses",
      "label": "SRD 5e Subclasses",
      "path": "packs/subclasses",
      "type": "Item",
      "system": "dnd5e",
      "private": false
    },
    {
      "name": "srd-monsters",
      "label": "SRD 5e Monsters",
      "path": "packs/monsters",
      "type": "Actor",
      "system": "dnd5e",
      "private": false
    },
    {
      "name": "srd-items",
      "label": "SRD 5e Items",
      "path": "packs/items",
      "type": "Item",
      "system": "dnd5e",
      "private": false
    },
    {
      "name": "srd-spells",
      "label": "SRD 5e Spells",
      "path": "packs/spells",
      "type": "Item",
      "system": "dnd5e",
      "private": false
    },
    {
      "name": "srd-rules",
      "label": "SRD 5e Rules",
      "path": "packs/rules",
      "type": "JournalEntry",
      "system": "dnd5e",
      "private": false
    },
    {
      "name": "srd-locations",
      "label": "SRD 5e Locations",
      "path": "packs/locations",
      "type": "Scene",
      "system": "dnd5e",
      "private": false
    }
  ],
  "relationships": {
    "requires": [
      {
        "id": "foundry-core-concepts",
        "type": "module",
        "compatibility": {
          "minimum": "0.1.0"
        }
      }
    ]
  },
  "url": "",
  "manifest": "",
  "download": ""
}
